odoo8_addon_base_ir_filters_company-8.0.1.0.0-py2.7-nspkg.pth
odoo8_addon_base_ir_filters_company-8.0.1.0.0.dist-info/DESCRIPTION.rst
odoo8_addon_base_ir_filters_company-8.0.1.0.0.dist-info/METADATA
odoo8_addon_base_ir_filters_company-8.0.1.0.0.dist-info/RECORD
odoo8_addon_base_ir_filters_company-8.0.1.0.0.dist-info/WHEEL
odoo8_addon_base_ir_filters_company-8.0.1.0.0.dist-info/metadata.json
odoo8_addon_base_ir_filters_company-8.0.1.0.0.dist-info/namespace_packages.txt
odoo8_addon_base_ir_filters_company-8.0.1.0.0.dist-info/top_level.txt
odoo_addons/base_ir_filters_company/README.rst
odoo_addons/base_ir_filters_company/__init__.py
odoo_addons/base_ir_filters_company/__openerp__.py
odoo_addons/base_ir_filters_company/post_install.py
odoo_addons/base_ir_filters_company/models/__init__.py
odoo_addons/base_ir_filters_company/models/ir_filters.py
odoo_addons/base_ir_filters_company/security/base_ir_filters_company_security.xml
odoo_addons/base_ir_filters_company/views/ir_filters.xml
