Metadata-Version: 2.0
Name: odoo8-addon-base-ir-filters-company
Version: 8.0.1.0.0
Summary: Filters by company
Home-page: http://www.acsone.eu
Author: Acsone SA/NV,Odoo Community Association (OCA)
Author-email: support@odoo-community.org
License: AGPL-3
Platform: UNKNOWN
Classifier: Programming Language :: Python :: 2.7
Classifier: Framework :: Odoo
Classifier: License :: OSI Approved :: GNU Affero General Public License v3
Requires-Dist: odoo (<9.0a,>=8.0a)
